full_todotxt/__init__.py
full_todotxt/__main__.py
full_todotxt/todo.py
full_todotxt-0.2.4.dist-info/LICENSE
full_todotxt-0.2.4.dist-info/METADATA
full_todotxt-0.2.4.dist-info/WHEEL
full_todotxt-0.2.4.dist-info/entry_points.txt
full_todotxt-0.2.4.dist-info/top_level.txt
full_todotxt-0.2.4.dist-info/RECORD
