Metadata-Version: 2.1
Name: full-todotxt
Version: 0.2.4
Summary: todotxt interactive interface that forces you to specify attributes
Home-page: https://github.com/seanbreckenridge/full_todotxt
Author: Sean Breckenridge
Author-email: "seanbrecke@gmail.com"
License: MIT
Keywords: todotxt todo.txt todo
Classifier: License :: OSI Approved :: MIT License
Classifier: Programming Language :: Python
Classifier: Programming Language :: Python :: 3
Classifier: Programming Language :: Python :: 3 :: Only
Classifier: Programming Language :: Python :: 3.8
Classifier: Programming Language :: Python :: 3.9
Classifier: Programming Language :: Python :: 3.10
Classifier: Programming Language :: Python :: 3.11
Requires-Python: >=3.8
License-File: LICENSE
Requires-Dist: autotui >=0.4.6
Requires-Dist: click >=8.0.0
Requires-Dist: dateparser >=1.1.0
Requires-Dist: prompt-toolkit >=3.0.5
Requires-Dist: pytodotxt >=1.5.0
Provides-Extra: testing
Requires-Dist: flake8 ; extra == 'testing'
Requires-Dist: mypy ; extra == 'testing'
